SudokuJson2Pdf-0.0.5.dist-info/METADATA
SudokuJson2Pdf-0.0.5.dist-info/metadata.json
SudokuJson2Pdf-0.0.5.dist-info/RECORD
SudokuJson2Pdf-0.0.5.dist-info/DESCRIPTION.rst
SudokuJson2Pdf-0.0.5.dist-info/WHEEL
SudokuJson2Pdf-0.0.5.dist-info/top_level.txt
SudokuJson2Pdf-0.0.5.data/scripts/sudoku2pdf.py
sudoku_json2pdf/sudoku2pdf.py
sudoku_json2pdf/__init__.py
