Metadata-Version: 2.0
Name: SudokuJson2Pdf
Version: 0.0.5
Summary: This project provides a tool which convert json file of sudokuinformation to pdf.
Home-page: https://github.com/yassu/SudokuJson2Pdf
Author: Yassu
Author-email: mathyassu@gmail.com
License: Released Under the Apache license
Requires-Dist: reportlab
